awesomeNations/__init__.py
awesomeNations/connection.py
awesomeNations/customMethods.py
awesomeNations/exceptions.py
awesomeNations/internalTools.py
awesomeNations/main.py
awesomenations-2.0.0.dist-info/licenses/License
awesomenations-2.0.0.dist-info/METADATA
awesomenations-2.0.0.dist-info/WHEEL
awesomenations-2.0.0.dist-info/top_level.txt
awesomenations-2.0.0.dist-info/RECORD
