Metadata-Version: 2.4
Name: AwesomeNations
Version: 2.0.0
Summary: A simple and cozy wrapper for NationStates
Author-email: Orly Neto <orly2carvalhoneto@gmail.com>
Maintainer-email: Orly Neto <orly2carvalhoneto@gmail.com>
License-Expression: MIT
Project-URL: Repository, https://github.com/Stalot/AwesomeNations
Project-URL: Issues, https://github.com/Stalot/AwesomeNations/issues
Project-URL: Changelog, https://github.com/Stalot/AwesomeNations/blob/main/CHANGELOG.md
Keywords: NationStates,API wrapper,NationStates wrapper,wrapper
Classifier: Development Status :: 5 - Production/Stable
Classifier: Intended Audience :: Developers
Classifier: Programming Language :: Python
Classifier: Operating System :: OS Independent
Requires-Python: >=3.10
License-File: License
Requires-Dist: urllib3==2.3.0
Requires-Dist: xmltodict==0.14.2
Dynamic: license-file
